streamlit_cookies_manager/__init__.py
streamlit_cookies_manager/cookie_manager.py
streamlit_cookies_manager/encrypted_cookie_manager.py
streamlit_cookies_manager/package-lock.json
streamlit_cookies_manager/package.json
streamlit_cookies_manager/tsconfig.json
streamlit_cookies_manager/public/index.html
streamlit_cookies_manager/src/index.ts
streamlit_cookies_manager/src/react-app-env.d.ts
streamlit_cookies_manager/build/asset-manifest.json
streamlit_cookies_manager/build/index.html
streamlit_cookies_manager/build/static/js/main.52df28f0.js
streamlit_cookies_manager/build/static/js/main.52df28f0.js.LICENSE.txt
streamlit_cookies_manager/build/static/js/main.52df28f0.js.map
streamlit_cookies_manager_v2-0.3.1.dist-info/METADATA
streamlit_cookies_manager_v2-0.3.1.dist-info/WHEEL
streamlit_cookies_manager_v2-0.3.1.dist-info/licenses/LICENSE
streamlit_cookies_manager_v2-0.3.1.dist-info/RECORD
