Metadata-Version: 2.4
Name: streamlit-cookies-manager-v2
Version: 0.3.1
Summary: Access and save cookies from Streamlit - Modernized fork with st.cache_data fix, uv package manager, and updated Node dependencies
Project-URL: Homepage, https://github.com/JohnDoeData/streamlit-cookies-manager
Project-URL: Repository, https://github.com/JohnDoeData/streamlit-cookies-manager.git
Project-URL: Bug Tracker, https://github.com/JohnDoeData/streamlit-cookies-manager/issues
Project-URL: Original Project, https://github.com/ktosiek/streamlit-cookies-manager
Author-email: Tomasz Kontusz <tomasz.kontusz@gmail.com>
Maintainer-email: JohnDoeData <johndoe_data@outlook.com>
License: Apache-2.0
License-File: LICENSE
Keywords: browser-storage,cookies,session-management,streamlit,streamlit-component
Classifier: Development Status :: 4 - Beta
Classifier: Intended Audience :: Developers
Classifier: License :: OSI Approved :: Apache Software License
Classifier: Programming Language :: Python :: 3
Classifier: Programming Language :: Python :: 3.9
Classifier: Programming Language :: Python :: 3.10
Classifier: Programming Language :: Python :: 3.11
Classifier: Programming Language :: Python :: 3.12
Classifier: Programming Language :: Python :: 3.13
Classifier: Topic :: Software Development :: Libraries :: Python Modules
Requires-Python: >=3.9
Requires-Dist: cryptography
Requires-Dist: streamlit>=1.18.0
Provides-Extra: dev
Requires-Dist: black>=23.0.0; extra == 'dev'
Requires-Dist: pytest>=7.0.0; extra == 'dev'
Requires-Dist: ruff>=0.1.0; extra == 'dev'
